.gitignore
.gitlab-ci.yml
AUTHORS
CMakeLists.txt
LICENSE
README.md
dune-polygongrid.pc.in
dune.module
pyproject.toml
setup.py
cmake/modules/CMakeLists.txt
cmake/modules/DunePolygongridMacros.cmake
dune/CMakeLists.txt
dune/polygongrid/CMakeLists.txt
dune/polygongrid/capabilities.hh
dune/polygongrid/declaration.hh
dune/polygongrid/dgf.hh
dune/polygongrid/entity.hh
dune/polygongrid/entityiterator.hh
dune/polygongrid/entityseed.hh
dune/polygongrid/geometry.hh
dune/polygongrid/grid.hh
dune/polygongrid/gridfactory.hh
dune/polygongrid/gridfamily.hh
dune/polygongrid/gridview.hh
dune/polygongrid/identitymatrix.hh
dune/polygongrid/idset.hh
dune/polygongrid/indexset.hh
dune/polygongrid/intersection.hh
dune/polygongrid/iteratortags.hh
dune/polygongrid/mesh.cc
dune/polygongrid/mesh.hh
dune/polygongrid/meshobjects.hh
dune/polygongrid/multivector.hh
dune/polygongrid/subentity.hh
python/CMakeLists.txt
python/dune/CMakeLists.txt
python/dune/polygongrid/CMakeLists.txt
python/dune/polygongrid/__init__.py
python/dune/polygongrid/blossoms.py
python/dune/polygongrid/voronoi.py
python/dune_polygongrid.egg-info/PKG-INFO
python/dune_polygongrid.egg-info/SOURCES.txt
python/dune_polygongrid.egg-info/dependency_links.txt
python/dune_polygongrid.egg-info/requires.txt
python/dune_polygongrid.egg-info/top_level.txt
test/CMakeLists.txt
test/test-mesh.cc
test/test-polygongrid.cc
test/test-polygongrid.py